notifier/__init__.py
notifier_function-1.5.1.dist-info/LICENSE
notifier_function-1.5.1.dist-info/METADATA
notifier_function-1.5.1.dist-info/WHEEL
notifier_function-1.5.1.dist-info/top_level.txt
notifier_function-1.5.1.dist-info/RECORD
