Metadata-Version: 2.1
Name: notifier-function
Version: 1.5.1
Summary: Notify you when a function finished with option to send a email
Home-page: https://github.com/enmanuel-mag/notifier_function
Author: Enmanuel Magallanes Pinargote
Author-email: fmagalla@fiec.espol.edu.ec
License: UNKNOWN
Platform: UNKNOWN
Classifier: Programming Language :: Python :: 3
Classifier: License :: OSI Approved :: MIT License
Classifier: Operating System :: OS Independent
Requires-Python: >=3.6
Requires-Dist: requests
Requires-Dist: py-notifier
